pyveoliaidf/__init__.py
pyveoliaidf/__main__.py
pyveoliaidf/client.py
pyveoliaidf/enum.py
pyveoliaidf/version.py
pyveoliaidf/webdriverwrapper.py
pyveoliaidf/webelementwrapper.py
pyveoliaidf-0.4.5.dist-info/licenses/LICENSE.md
tests/__init__.py
tests/test_client.py
pyveoliaidf-0.4.5.dist-info/METADATA
pyveoliaidf-0.4.5.dist-info/WHEEL
pyveoliaidf-0.4.5.dist-info/entry_points.txt
pyveoliaidf-0.4.5.dist-info/top_level.txt
pyveoliaidf-0.4.5.dist-info/RECORD
