Metadata-Version: 2.4
Name: pyveoliaidf
Version: 0.4.5
Summary: Retrieve water consumption from Veolia Ile-de-France web site (French Water Company)
Home-page: https://github.com/ssenart/pyveoliaidf
Download-URL: https://github.com/ssenart/pyveoliaidf/releases
Author: Stephane Senart
Author-email: stephane.senart@gmail.com
License: MIT
Project-URL: Home, https://github.com/ssenart/pyveoliaidf
Project-URL: Source, https://github.com/ssenart/pyveoliaidf
Project-URL: Issues, https://github.com/ssenart/pyveoliaidf/issues
Project-URL: Changelog, https://github.com/ssenart/pyveoliaidf/blob/master/CHANGELOG.md
Project-URL: Download, https://pypi.org/project/pyveoliaidf
Keywords: Resource,Water,Meter,Consumption,Veolia,Ile-de-France
Platform: any
Classifier: Development Status :: 5 - Production/Stable
Classifier: Topic :: Software Development :: Libraries
Classifier: Operating System :: OS Independent
Classifier: Programming Language :: Python :: 3.9
Classifier: Programming Language :: Python :: 3.10
Classifier: Programming Language :: Python :: 3.11
Classifier: Programming Language :: Python :: 3.12
Requires-Python: >=3.9
License-File: LICENSE.md
Requires-Dist: selenium==4.17.2
Requires-Dist: openpyxl>=2.6.3
Dynamic: download-url
Dynamic: license-file
